{
    "company_name": "Mesari Production",
    "tagline": "Creative • Professional • Trusted",
    "description": "Mesari Production provides high–quality creative services including photography, videography, and digital content creation. We combine professionalism with creative vision to deliver impactful results.",
    "email": "contact@mesariproduction.com",
    "phone": "02112345678",
    "whatsapp": "081234567890",
    "address": "Jl. Melati No. 45",
    "city": "Jakarta Selatan",
    "province": "DKI Jakarta",
    "postal_code": "12120",
    "google_map_url": "https://maps.google.com/?q=Jakarta+Selatan",
    "working_hours": "Mon–Sun, 09:00–18:00",
    "instagram": "@mesariproduction",
    "tiktok": "@mesariproduction",
    "facebook": "mesariproduction"
}
